trip_kinematics/KinematicGroup.py
trip_kinematics/Robot.py
trip_kinematics/Solver.py
trip_kinematics/Transformation.py
trip_kinematics/Utility.py
trip_kinematics/__init__.py
trip_kinematics/urdf_parser.py
trip_robots/__init__.py
trip_robots/excavator_rr.py
trip_robots/triped.py
trip_robots/triped_leg.py
trip_kinematics-1.0.4.dist-info/METADATA
trip_kinematics-1.0.4.dist-info/WHEEL
trip_kinematics-1.0.4.dist-info/top_level.txt
trip_kinematics-1.0.4.dist-info/RECORD
