Metadata-Version: 2.1
Name: trip-kinematics
Version: 1.0.4
Summary: ...
Author: Torben Miller, Jan Baumgärtner
License: MIT
Platform: UNKNOWN
Requires-Dist: casadi (>=3.5.5)
Requires-Dist: numpy (<1.20.0,>=1.17.4)
Requires-Dist: defusedxml (>=0.5)
